{
	"archive" : {},
	"artifacts" : 
	[
		{
			"path" : "libcarladata_idl.a"
		}
	],
	"backtrace" : 1,
	"backtraceGraph" : 
	{
		"commands" : 
		[
			"add_library",
			"target_link_libraries",
			"target_include_directories",
			"OPENDDS_TARGET_SOURCES",
			"include_directories",
			"target_sources",
			"opendds_add_idl_or_header_files",
			"opendds_target_generated_dependencies",
			"opendds_target_idl_sources"
		],
		"files" : 
		[
			"CMakeLists.txt",
			"/opt/OpenDDS/share/cmake/OpenDDS/api_macros.cmake",
			"/opt/OpenDDS/share/cmake/OpenDDS/dds_idl_sources.cmake"
		],
		"nodes" : 
		[
			{
				"file" : 0
			},
			{
				"command" : 0,
				"file" : 0,
				"line" : 12,
				"parent" : 0
			},
			{
				"command" : 1,
				"file" : 0,
				"line" : 14,
				"parent" : 0
			},
			{
				"command" : 3,
				"file" : 0,
				"line" : 13,
				"parent" : 0
			},
			{
				"command" : 2,
				"file" : 1,
				"line" : 275,
				"parent" : 3
			},
			{
				"command" : 4,
				"file" : 0,
				"line" : 20,
				"parent" : 0
			},
			{
				"command" : 8,
				"file" : 1,
				"line" : 237,
				"parent" : 3
			},
			{
				"command" : 7,
				"file" : 2,
				"line" : 280,
				"parent" : 6
			},
			{
				"command" : 6,
				"file" : 2,
				"line" : 82,
				"parent" : 7
			},
			{
				"command" : 5,
				"file" : 2,
				"line" : 26,
				"parent" : 8
			},
			{
				"command" : 5,
				"file" : 2,
				"line" : 26,
				"parent" : 8
			},
			{
				"command" : 5,
				"file" : 2,
				"line" : 26,
				"parent" : 8
			},
			{
				"command" : 5,
				"file" : 2,
				"line" : 26,
				"parent" : 8
			},
			{
				"command" : 5,
				"file" : 2,
				"line" : 26,
				"parent" : 8
			},
			{
				"command" : 5,
				"file" : 2,
				"line" : 26,
				"parent" : 8
			},
			{
				"command" : 5,
				"file" : 2,
				"line" : 26,
				"parent" : 8
			},
			{
				"command" : 5,
				"file" : 2,
				"line" : 26,
				"parent" : 8
			},
			{
				"command" : 6,
				"file" : 2,
				"line" : 83,
				"parent" : 7
			},
			{
				"command" : 5,
				"file" : 2,
				"line" : 26,
				"parent" : 17
			},
			{
				"command" : 5,
				"file" : 2,
				"line" : 84,
				"parent" : 7
			}
		]
	},
	"compileGroups" : 
	[
		{
			"compileCommandFragments" : 
			[
				{
					"fragment" : "-w  "
				},
				{
					"backtrace" : 2,
					"fragment" : "-pthread"
				}
			],
			"defines" : 
			[
				{
					"backtrace" : 2,
					"define" : "__ACE_INLINE__"
				}
			],
			"includes" : 
			[
				{
					"backtrace" : 4,
					"path" : "/home/fev/MEGA/work/other/acc-demo-wo-obj-detection/build/opendds_generated"
				},
				{
					"backtrace" : 5,
					"path" : "/home/fev/MEGA/work/other/acc-demo-wo-obj-detection/include"
				},
				{
					"backtrace" : 5,
					"path" : "/home/fev/MEGA/work/other/acc-demo-wo-obj-detection/libcarla-install/include"
				},
				{
					"backtrace" : 5,
					"path" : "/home/fev/MEGA/work/other/acc-demo-wo-obj-detection/libcarla-install/include/system"
				},
				{
					"backtrace" : 2,
					"isSystem" : true,
					"path" : "/opt/OpenDDS/include"
				},
				{
					"backtrace" : 2,
					"isSystem" : true,
					"path" : "/opt/OpenDDS/include/orbsvcs"
				}
			],
			"language" : "CXX",
			"sourceIndexes" : 
			[
				9,
				10,
				11
			]
		}
	],
	"id" : "carladata_idl::@6890427a1f51a3e7e1df",
	"name" : "carladata_idl",
	"nameOnDisk" : "libcarladata_idl.a",
	"paths" : 
	{
		"build" : ".",
		"source" : "."
	},
	"sourceGroups" : 
	[
		{
			"name" : "Generated Files",
			"sourceIndexes" : 
			[
				0,
				1,
				2,
				3,
				4,
				5,
				6,
				7,
				9,
				10,
				11
			]
		},
		{
			"name" : "IDL Files",
			"sourceIndexes" : 
			[
				8
			]
		},
		{
			"name" : "CMake Rules",
			"sourceIndexes" : 
			[
				12
			]
		}
	],
	"sources" : 
	[
		{
			"backtrace" : 9,
			"isGenerated" : true,
			"path" : "build/opendds_generated/CarlaDataTypeSupport.idl",
			"sourceGroupIndex" : 0
		},
		{
			"backtrace" : 10,
			"isGenerated" : true,
			"path" : "build/opendds_generated/CarlaDataTypeSupportImpl.h",
			"sourceGroupIndex" : 0
		},
		{
			"backtrace" : 11,
			"isGenerated" : true,
			"path" : "build/opendds_generated/CarlaDataC.h",
			"sourceGroupIndex" : 0
		},
		{
			"backtrace" : 12,
			"isGenerated" : true,
			"path" : "build/opendds_generated/CarlaDataC.inl",
			"sourceGroupIndex" : 0
		},
		{
			"backtrace" : 13,
			"isGenerated" : true,
			"path" : "build/opendds_generated/CarlaDataS.h",
			"sourceGroupIndex" : 0
		},
		{
			"backtrace" : 14,
			"isGenerated" : true,
			"path" : "build/opendds_generated/CarlaDataTypeSupportC.h",
			"sourceGroupIndex" : 0
		},
		{
			"backtrace" : 15,
			"isGenerated" : true,
			"path" : "build/opendds_generated/CarlaDataTypeSupportC.inl",
			"sourceGroupIndex" : 0
		},
		{
			"backtrace" : 16,
			"isGenerated" : true,
			"path" : "build/opendds_generated/CarlaDataTypeSupportS.h",
			"sourceGroupIndex" : 0
		},
		{
			"backtrace" : 18,
			"path" : "CarlaData.idl",
			"sourceGroupIndex" : 1
		},
		{
			"backtrace" : 19,
			"compileGroupIndex" : 0,
			"isGenerated" : true,
			"path" : "build/opendds_generated/CarlaDataTypeSupportImpl.cpp",
			"sourceGroupIndex" : 0
		},
		{
			"backtrace" : 19,
			"compileGroupIndex" : 0,
			"isGenerated" : true,
			"path" : "build/opendds_generated/CarlaDataC.cpp",
			"sourceGroupIndex" : 0
		},
		{
			"backtrace" : 19,
			"compileGroupIndex" : 0,
			"isGenerated" : true,
			"path" : "build/opendds_generated/CarlaDataTypeSupportC.cpp",
			"sourceGroupIndex" : 0
		},
		{
			"backtrace" : 0,
			"isGenerated" : true,
			"path" : "build/opendds_generated/CarlaDataC.h.rule",
			"sourceGroupIndex" : 2
		}
	],
	"type" : "STATIC_LIBRARY"
}
